ohmygod/__init__.py
ohmygod/main.py
ohmygod/messenger/__init__.py
ohmygod/messenger/buddha.py
ohmygod/messenger/messenger.py
ohmygod/utils.py
ohmygod-0.2.1.dist-info/LICENSE
ohmygod-0.2.1.dist-info/METADATA
ohmygod-0.2.1.dist-info/WHEEL
ohmygod-0.2.1.dist-info/RECORD
