Metadata-Version: 2.1
Name: ohmygod
Version: 0.2.1
Summary: Rich CLI tool powered by gods
Home-page: https://github.com/aintbe/ohmygod
License: MIT
Author: Sori Lim
Author-email: aint.imsorry@gmail.com
Requires-Python: >=3.10,<4.0
Classifier: License :: OSI Approved :: MIT License
Classifier: Programming Language :: Python :: 3
Classifier: Programming Language :: Python :: 3.10
Classifier: Programming Language :: Python :: 3.11
Classifier: Programming Language :: Python :: 3.12
Classifier: Programming Language :: Python :: 3.13
Requires-Dist: colorama (>=0.4,<0.5)
Requires-Dist: readchar (>=4.0.0,<5.0.0)
Requires-Dist: rich (>=12.4.4)
